LICENSE
MANIFEST.in
PATENTS
README.rst
setup.cfg
setup.py
sparts/__init__.py
sparts/collections.py
sparts/compat.py
sparts/counters.py
sparts/ctx.py
sparts/daemon.py
sparts/deps.py
sparts/fileutils.py
sparts/runit.py
sparts/sparts.py
sparts/timer.py
sparts/vservice.py
sparts/vtask.py
sparts.egg-info/PKG-INFO
sparts.egg-info/SOURCES.txt
sparts.egg-info/dependency_links.txt
sparts.egg-info/pbr.json
sparts.egg-info/requires.txt
sparts.egg-info/top_level.txt
sparts/../thrift/fb303.thrift
sparts/fb303/FacebookService.py
sparts/fb303/__init__.py
sparts/fb303/constants.py
sparts/fb303/dbus.py
sparts/fb303/ttypes.py
sparts/gen/__init__.py
sparts/gen/fb303/FacebookService.py
sparts/gen/fb303/__init__.py
sparts/gen/fb303/constants.py
sparts/gen/fb303/ttypes.py
sparts/gen/sparts_examples/SpartsBarService.py
sparts/gen/sparts_examples/SpartsFooService.py
sparts/gen/sparts_examples/__init__.py
sparts/gen/sparts_examples/constants.py
sparts/gen/sparts_examples/ttypes.py
sparts/tasks/__init__.py
sparts/tasks/dbus.py
sparts/tasks/fb303.py
sparts/tasks/file.py
sparts/tasks/periodic.py
sparts/tasks/poller.py
sparts/tasks/queue.py
sparts/tasks/select.py
sparts/tasks/tornado.py
sparts/tasks/tornado_thrift.py
sparts/tasks/tui.py
sparts/tasks/twisted.py
sparts/tasks/twisted_command.py
sparts/tasks/thrift/__init__.py
sparts/tasks/thrift/cppserver.py
sparts/tasks/thrift/handler.py
sparts/tasks/thrift/nbserver.py
sparts/tasks/thrift/server.py
sparts/tests/__init__.py
sparts/tests/base.py
sparts/tests/dummy.py
sparts/thrift/__init__.py
sparts/thrift/client.py
sparts/thrift/compiler.py