Metadata-Version: 1.1
Name: sparts
Version: 0.7.3
Summary: Build services in python with as little code as possible
Home-page: http://github.com/facebook/sparts
Author: Peter Ruibal
Author-email: ruibalp@gmail.com
License: BSD+
Download-URL: https://github.com/facebook/sparts/archive/0.7.3.tar.gz
Keywords: service boostrap daemon thrift tornado
Platform: UNKNOWN
Classifier: Development Status :: 3 - Alpha
Classifier: Topic :: Utilities
Classifier: Topic :: Software Development :: Libraries :: Application Frameworks
Classifier: License :: OSI Approved :: BSD License
Classifier: Programming Language :: Python :: 2.6
Classifier: Programming Language :: Python :: 2.7
Classifier: Programming Language :: Python :: 3.2
Classifier: Programming Language :: Python :: 3.3
Classifier: Programming Language :: Python :: 3.4
